sfm/__init__.py
sfm/__init__.pyc
sfm/_version.py
sfm/_version.pyc
sfm/binarysearch.py
sfm/binarysearch.pyc
sfm/decorator.py
sfm/decorator.pyc
sfm/dtree.py
sfm/dtree.pyc
sfm/exception_mate.py
sfm/exception_mate.pyc
sfm/fingerprint.py
sfm/fingerprint.pyc
sfm/flow.py
sfm/flow.pyc
sfm/geo_search.py
sfm/geo_search.pyc
sfm/iterable.py
sfm/iterable.pyc
sfm/lines_count.py
sfm/lines_count.pyc
sfm/marshmallow_fields.py
sfm/marshmallow_fields.pyc
sfm/matplot_mate.py
sfm/nameddict.py
sfm/nameddict.pyc
sfm/obj_file_io.py
sfm/obj_file_io.pyc
sfm/rerecipe.py
sfm/rerecipe.pyc
sfm/rnd.py
sfm/rnd.pyc
sfm/str_encoding.py
sfm/str_encoding.pyc
sfm/string_match.py
sfm/string_match.pyc
sfm/textformatter.py
sfm/textformatter.pyc
sfm/timer.py
sfm/timer.pyc
sfm/winzip.py
sfm/winzip.pyc
sfm/ziplib.py
sfm/ziplib.pyc
sfm-0.0.17.dist-info/AUTHORS.rst
sfm-0.0.17.dist-info/LICENSE.txt
sfm-0.0.17.dist-info/METADATA
sfm-0.0.17.dist-info/WHEEL
sfm-0.0.17.dist-info/top_level.txt
sfm-0.0.17.dist-info/RECORD
